{
  "schema_version": 1,
  "name": "GooFit",
  "upstream_url": "https://github.com/GooFit/GooFit",
  "fork_url": "https://github.com/jeffdaily/GooFit",
  "fork_default_branch": "master",
  "priority": 0.0,
  "ext_type": "cmake",
  "adopted_at": "2026-06-05T00:04:16Z",
  "updated_at": "2026-06-12T00:02:46Z",
  "head_sha": "d95236e57ecd6cfb94e53d731b104b694d4da2ea",
  "depends_on": [],
  "platforms": {
    "linux-gfx90a": {
      "state": "porting",
      "blocked": true,
      "blocked_reason": "Build/link blocker RESOLVED (cross-TU device visibility fixed via -fgpu-rdc + OBJECT-libs-to-single-shared-lib device link; core+basic+combine PDFs and 24 test/example exes build and link on gfx90a). NEW blocker: unbinned NLL fits diverge to a parameter bound because the device reads garbage normalization values (6.25e-310 uninitialized-double pattern) from the hipMemcpyToSymbol-published __device__ d_normalizations during the per-event reduction; analytic normalize() and per-event device eval are correct in isolation. See notes.md attempt 2 for the minimal repro and next steps. Physics PDFs scoped out (GOOFIT_PHYSICS=OFF; MCBooster+device Eigen complex inverse deferred, WIP patch saved).",
      "validated_sha": null,
      "started_at": "2026-06-05T00:09:14Z",
      "completed_at": null,
      "updated_at": "2026-06-12T00:02:46Z",
      "stats": {
        "tokens_total": 0,
        "tokens_approx": true,
        "wall_seconds": {
          "thinking": 0,
          "compile": 0,
          "test": 0,
          "misc": 0
        },
        "session_count": 0,
        "first_session_at": null,
        "last_session_at": null
      },
      "last_agent": "planner"
    },
    "linux-gfx1100": {
      "state": "blocked-needs-gfx90a",
      "blocked": false,
      "blocked_reason": null,
      "validated_sha": null,
      "started_at": null,
      "completed_at": null,
      "updated_at": "2026-06-05T00:04:16Z",
      "stats": {
        "tokens_total": 0,
        "tokens_approx": true,
        "wall_seconds": {
          "thinking": 0,
          "compile": 0,
          "test": 0,
          "misc": 0
        },
        "session_count": 0,
        "first_session_at": null,
        "last_session_at": null
      }
    },
    "windows-gfx1101": {
      "state": "blocked-needs-gfx90a",
      "blocked": false,
      "blocked_reason": null,
      "validated_sha": null,
      "started_at": null,
      "completed_at": null,
      "updated_at": "2026-06-05T00:04:16Z",
      "stats": {
        "tokens_total": 0,
        "tokens_approx": true,
        "wall_seconds": {
          "thinking": 0,
          "compile": 0,
          "test": 0,
          "misc": 0
        },
        "session_count": 0,
        "first_session_at": null,
        "last_session_at": null
      }
    },
    "windows-gfx1201": {
      "state": "blocked-needs-gfx90a",
      "blocked": false,
      "blocked_reason": null,
      "validated_sha": null,
      "started_at": null,
      "completed_at": null,
      "updated_at": "2026-06-05T00:04:16Z",
      "stats": {
        "tokens_total": 0,
        "tokens_approx": true,
        "wall_seconds": {
          "thinking": 0,
          "compile": 0,
          "test": 0,
          "misc": 0
        },
        "session_count": 0,
        "first_session_at": null,
        "last_session_at": null
      }
    },
    "windows-gfx1151": {
      "state": "blocked-needs-gfx90a",
      "blocked": false,
      "blocked_reason": null,
      "validated_sha": null,
      "started_at": null,
      "completed_at": null,
      "updated_at": "2026-06-05T00:04:16Z",
      "stats": {
        "tokens_total": 0,
        "tokens_approx": true,
        "wall_seconds": {
          "thinking": 0,
          "compile": 0,
          "test": 0,
          "misc": 0
        },
        "session_count": 0,
        "first_session_at": null,
        "last_session_at": null
      }
    }
  }
}
