{
  "schema_version": 1,
  "name": "CPM.cu",
  "upstream_url": "https://github.com/OpenBMB/CPM.cu",
  "fork_url": null,
  "fork_default_branch": "main",
  "priority": 3.979,
  "ext_type": "torch-extension",
  "adopted_at": "2026-05-30T03:26:34Z",
  "updated_at": "2026-06-04T19:41:52Z",
  "head_sha": null,
  "platforms": {
    "linux-gfx90a": {
      "state": "planned",
      "blocked": true,
      "blocked_reason": "CUTLASS/CuTe FlashAttention-2 + Marlin W4A16 raw sm80 PTX (mma.sync/ldmatrix/cp.async/lop3/prmt); monolithic module hard-includes flash_api.hpp so no portable-only validatable slice -- multi-week AMD-native CK/MFMA reimplement, not a mechanical port. Defer (jeff: skip-vs-fund-rewrite).",
      "validated_sha": null,
      "started_at": null,
      "completed_at": null,
      "updated_at": "2026-06-02T05:40:30Z",
      "stats": {
        "tokens_total": 0,
        "tokens_approx": true,
        "wall_seconds": {
          "thinking": 0,
          "compile": 0,
          "test": 0,
          "misc": 0
        },
        "session_count": 0,
        "first_session_at": null,
        "last_session_at": null
      },
      "last_agent": "planner"
    },
    "linux-gfx1100": {
      "state": "blocked-needs-gfx90a",
      "blocked": false,
      "blocked_reason": null,
      "validated_sha": null,
      "started_at": null,
      "completed_at": null,
      "updated_at": "2026-05-30T03:26:34Z",
      "stats": {
        "tokens_total": 0,
        "tokens_approx": true,
        "wall_seconds": {
          "thinking": 0,
          "compile": 0,
          "test": 0,
          "misc": 0
        },
        "session_count": 0,
        "first_session_at": null,
        "last_session_at": null
      }
    },
    "windows-gfx1101": {
      "state": "blocked-needs-gfx90a",
      "blocked": false,
      "blocked_reason": null,
      "validated_sha": null,
      "started_at": null,
      "completed_at": null,
      "updated_at": "2026-06-04T19:41:52Z",
      "stats": {
        "tokens_total": 0,
        "tokens_approx": true,
        "wall_seconds": {
          "thinking": 0,
          "compile": 0,
          "test": 0,
          "misc": 0
        },
        "session_count": 0,
        "first_session_at": null,
        "last_session_at": null
      }
    },
    "windows-gfx1201": {
      "state": "blocked-needs-gfx90a",
      "blocked": false,
      "blocked_reason": null,
      "validated_sha": null,
      "started_at": null,
      "completed_at": null,
      "updated_at": "2026-06-04T19:41:52Z",
      "stats": {
        "tokens_total": 0,
        "tokens_approx": true,
        "wall_seconds": {
          "thinking": 0,
          "compile": 0,
          "test": 0,
          "misc": 0
        },
        "session_count": 0,
        "first_session_at": null,
        "last_session_at": null
      }
    },
    "windows-gfx1151": {
      "state": "blocked-needs-gfx90a",
      "blocked": true,
      "blocked_reason": "windows-gfx1151 host retired (superseded by the gfx1101/gfx1201 machine); validation moved to windows-gfx1101 and windows-gfx1201",
      "validated_sha": null,
      "started_at": null,
      "completed_at": null,
      "updated_at": "2026-06-04T19:41:52Z",
      "stats": {
        "tokens_total": 0,
        "tokens_approx": true,
        "wall_seconds": {
          "thinking": 0,
          "compile": 0,
          "test": 0,
          "misc": 0
        },
        "session_count": 0,
        "first_session_at": null,
        "last_session_at": null
      }
    }
  }
}
