{
  "schema_version": 1,
  "name": "brian2cuda",
  "upstream_url": "https://github.com/brian-team/brian2cuda",
  "fork_url": "https://github.com/jeffdaily/brian2cuda",
  "fork_default_branch": "master",
  "priority": 0.0,
  "ext_type": "codegen",
  "adopted_at": "2026-06-05T04:44:12Z",
  "updated_at": "2026-06-09T14:41:44Z",
  "head_sha": "8685120a24355b640b974d9f4c9e09e86edda7e0",
  "depends_on": [],
  "platforms": {
    "linux-gfx90a": {
      "state": "completed",
      "blocked": false,
      "blocked_reason": null,
      "validated_sha": "8685120a24355b640b974d9f4c9e09e86edda7e0",
      "started_at": "2026-06-05T08:30:52Z",
      "completed_at": "2026-06-08T15:19:15Z",
      "updated_at": "2026-06-09T14:41:44Z",
      "stats": {
        "tokens_total": 0,
        "tokens_approx": true,
        "wall_seconds": {
          "thinking": 0,
          "compile": 0,
          "test": 0,
          "misc": 0
        },
        "session_count": 0,
        "first_session_at": null,
        "last_session_at": null
      },
      "last_agent": "validator",
      "carry_forward": {
        "from": "94a9869",
        "to": "cf2c518459e9d3b892256679803a3a18ec784387",
        "method": "source-class",
        "class": "doc-only",
        "detail": "no changes",
        "at": "2026-06-09T14:40:34Z"
      }
    },
    "linux-gfx1100": {
      "state": "completed",
      "blocked": false,
      "blocked_reason": null,
      "validated_sha": "8685120a24355b640b974d9f4c9e09e86edda7e0",
      "started_at": null,
      "completed_at": "2026-06-08T17:06:12Z",
      "updated_at": "2026-06-09T14:41:44Z",
      "stats": {
        "tokens_total": 0,
        "tokens_approx": true,
        "wall_seconds": {
          "thinking": 0,
          "compile": 0,
          "test": 0,
          "misc": 0
        },
        "session_count": 0,
        "first_session_at": null,
        "last_session_at": null
      },
      "last_agent": "validator",
      "carry_forward": {
        "from": "94a9869",
        "to": "cf2c518459e9d3b892256679803a3a18ec784387",
        "method": "source-class",
        "class": "doc-only",
        "detail": "no changes",
        "at": "2026-06-09T14:40:34Z"
      }
    },
    "windows-gfx1101": {
      "state": "port-ready",
      "blocked": false,
      "blocked_reason": null,
      "validated_sha": null,
      "started_at": null,
      "completed_at": null,
      "updated_at": "2026-06-05T08:47:28Z",
      "stats": {
        "tokens_total": 0,
        "tokens_approx": true,
        "wall_seconds": {
          "thinking": 0,
          "compile": 0,
          "test": 0,
          "misc": 0
        },
        "session_count": 0,
        "first_session_at": null,
        "last_session_at": null
      }
    },
    "windows-gfx1201": {
      "state": "completed",
      "blocked": false,
      "blocked_reason": null,
      "validated_sha": "8685120a24355b640b974d9f4c9e09e86edda7e0",
      "started_at": null,
      "completed_at": "2026-06-08T13:52:53Z",
      "updated_at": "2026-06-09T14:41:44Z",
      "stats": {
        "tokens_total": 0,
        "tokens_approx": true,
        "wall_seconds": {
          "thinking": 0,
          "compile": 0,
          "test": 0,
          "misc": 0
        },
        "session_count": 0,
        "first_session_at": null,
        "last_session_at": null
      },
      "last_agent": "validator",
      "carry_forward": {
        "from": "94a9869",
        "to": "cf2c518459e9d3b892256679803a3a18ec784387",
        "method": "source-class",
        "class": "doc-only",
        "detail": "no changes",
        "at": "2026-06-09T14:40:34Z"
      }
    },
    "windows-gfx1151": {
      "state": "port-ready",
      "blocked": false,
      "blocked_reason": null,
      "validated_sha": null,
      "started_at": null,
      "completed_at": null,
      "updated_at": "2026-06-05T08:47:28Z",
      "stats": {
        "tokens_total": 0,
        "tokens_approx": true,
        "wall_seconds": {
          "thinking": 0,
          "compile": 0,
          "test": 0,
          "misc": 0
        },
        "session_count": 0,
        "first_session_at": null,
        "last_session_at": null
      }
    }
  }
}
